full_sub/full_sub.v
module full_sub(d,bor,a,b,bin);
input a,b,bin;
output d,bor;
assign d = a ^ b ^ bin;
assign bor = (~a & b) | (~(a ^ b) & bin);
endmodule

full_sub/full_sub_tb.v
module full_sub_tb;
reg a,b,bin;
wire d,bor;

full_sub uut(
.d(d),
.bor(bor),
.a(a),
.b(b),
.bin(bin)
);

initial begin
$dumpfile("fs.vcd");
$dumpvars(0,full_sub_tb);
a=0;b=0;bin=0;#10;
a=0;b=0;bin=1;#10;
a=0;b=1;bin=0;#10;
a=0;b=1;bin=1;#10;
a=1;b=0;bin=0;#10;
a=1;b=0;bin=1;#10;
a=1;b=1;bin=0;#10;
a=1;b=1;bin=1;#10;
end
endmodule

full_sub/fs.vcd
$date
	Wed Jan 22 17:58:22 2025
$end
$version
	Icarus Verilog
$end
$timescale
	1s
$end
$scope module full_sub_tb $end
$var wire 1 ! d $end
$var wire 1 " bor $end
$var reg 1 # a $end
$var reg 1 $ b $end
$var reg 1 % bin $end
$scope module uut $end
$var wire 1 # a $end
$var wire 1 $ b $end
$var wire 1 % bin $end
$var wire 1 " bor $end
$var wire 1 ! d $end
$upscope $end
$upscope $end
$enddefinitions $end
$comment Show the parameter values. $end
$dumpall
$end
#0
$dumpvars
0%
0$
0#
0"
0!
$end
#10
1"
1!
1%
#20
0%
1$
#30
0!
1%
#40
0"
1!
0%
0$
1#
#50
0!
1%
#60
0%
1$
#70
1"
1!
1%
