full_add/full_add.v
module full_add(s,c,a,b,cin);
input a,b,cin;
output s,c;
assign s = a^b^cin;
assign c = (a & b) | (b & cin)  | (cin & a) ;
endmodule

full_add/full_add_tb.v
module full_add_tb;
reg a,b,cin;
wire s,c;

full_add uut(
.s(s),
.c(c),
.a(a),
.b(b),
.cin(cin)
);

initial begin
$dumpfile("fa.vcd");
$dumpvars(0,full_add_tb);
a=0;b=0;cin=0;#10;
a=0;b=0;cin=1;#10;
a=0;b=1;cin=0;#10;
a=0;b=1;cin=1;#10;
a=1;b=0;cin=0;#10;
a=1;b=0;cin=1;#10;
a=1;b=1;cin=0;#10;
a=1;b=1;cin=1;#10;
end
endmodule

full_add/fa.vcd
$date
	Tue Jan 21 16:13:46 2025
$end
$version
	Icarus Verilog
$end
$timescale
	1s
$end
$scope module full_add_tb $end
$var wire 1 ! s $end
$var wire 1 " c $end
$var reg 1 # a $end
$var reg 1 $ b $end
$var reg 1 % cin $end
$scope module uut $end
$var wire 1 # a $end
$var wire 1 $ b $end
$var wire 1 " c $end
$var wire 1 % cin $end
$var wire 1 ! s $end
$upscope $end
$upscope $end
$enddefinitions $end
$comment Show the parameter values. $end
$dumpall
$end
#0
$dumpvars
0%
0$
0#
0"
0!
$end
#10
1!
1%
#20
0%
1$
#30
1"
0!
1%
#40
0"
1!
0%
0$
1#
#50
1"
0!
1%
#60
0%
1$
#70
1!
1%
